forms_builder/__init__.py
forms_builder/forms/signals.py
forms_builder/forms/models.py
forms_builder/forms/fields.py
forms_builder/forms/__init__.py
forms_builder/forms/forms.py
forms_builder/forms/admin.py
forms_builder/forms/utils.py
forms_builder/forms/settings.py
forms_builder/forms/tests.py
forms_builder/forms/urls.py
forms_builder/forms/views.py
forms_builder/forms/templatetags/__init__.py
forms_builder/forms/templatetags/forms_builder_tags.py
forms_builder/forms/migrations/__init__.py
forms_builder/forms/migrations/0001_initial.py
forms_builder/forms/migrations/0002_auto_20160418_0120.py
forms_builder/forms/locale/pl/LC_MESSAGES/django.mo
forms_builder/forms/locale/pl/LC_MESSAGES/django.po
forms_builder/forms/locale/pt_BR/LC_MESSAGES/django.mo
forms_builder/forms/locale/pt_BR/LC_MESSAGES/django.po
forms_builder/forms/locale/ru/LC_MESSAGES/django.mo
forms_builder/forms/locale/ru/LC_MESSAGES/django.po
forms_builder/forms/locale/zh/LC_MESSAGES/django.mo
forms_builder/forms/locale/zh/LC_MESSAGES/django.po
forms_builder/forms/locale/nl/LC_MESSAGES/django.mo
forms_builder/forms/locale/nl/LC_MESSAGES/django.po
forms_builder/forms/locale/nb/LC_MESSAGES/django.mo
forms_builder/forms/locale/nb/LC_MESSAGES/django.po
forms_builder/forms/locale/de/LC_MESSAGES/django.mo
forms_builder/forms/locale/de/LC_MESSAGES/django.po
forms_builder/forms/locale/fr/LC_MESSAGES/django.mo
forms_builder/forms/locale/fr/LC_MESSAGES/django.po
forms_builder/forms/locale/es/LC_MESSAGES/django.mo
forms_builder/forms/locale/es/LC_MESSAGES/django.po
forms_builder/forms/templates/forms/form_detail.html
forms_builder/forms/templates/forms/form_sent.html
forms_builder/forms/templates/forms/includes/built_form.html
forms_builder/forms/templates/admin/forms/change_list.html
forms_builder/forms/templates/admin/forms/entries.html
forms_builder/forms/templates/admin/forms/change_form.html
forms_builder/forms/templates/email_extras/form_response_copies.html
django_forms_builder-0.14.0.dist-info/RECORD
django_forms_builder-0.14.0.dist-info/metadata.json
django_forms_builder-0.14.0.dist-info/WHEEL
django_forms_builder-0.14.0.dist-info/DESCRIPTION.rst
django_forms_builder-0.14.0.dist-info/top_level.txt
django_forms_builder-0.14.0.dist-info/METADATA
