Metadata-Version: 1.1
Name: django-forms-builder
Version: 0.14.0
Summary: A Django reusable app providing the ability for admin users to create their own forms and report on their collected data.
Home-page: http://github.com/stephenmcd/django-forms-builder
Author: Stephen McDonald
Author-email: stephen.mc@gmail.com
License: BSD
Platform: UNKNOWN
Classifier: Development Status :: 5 - Production/Stable
Classifier: Environment :: Web Environment
Classifier: Intended Audience :: Developers
Classifier: Operating System :: OS Independent
Classifier: Programming Language :: Python
Classifier: Programming Language :: Python :: 2.7
Classifier: Programming Language :: Python :: 3
Classifier: Programming Language :: Python :: 3.4
Classifier: Programming Language :: Python :: 3.5
Classifier: Framework :: Django
Classifier: Topic :: Internet :: WWW/HTTP :: Dynamic Content
Classifier: Topic :: Internet :: WWW/HTTP :: Site Management
